<?xml version="1.0" encoding="WINDOWS-1252" standalone="no"?>
<!--This file is in the Girr (General IR Remote) format, see http://www.harctoolbox.org/Girr.html--><remotes xmlns="http://www.harctoolbox.org/Girr" xmlns:html="http://www.w3.org/1999/xhtml" xmlns:xsi="http://www.w3.org/2001/XMLSchema-instance" girrVersion="1.2" title="IrScrutinizer parametric export" xsi:schemaLocation="http://www.harctoolbox.org/Girr http://www.harctoolbox.org/schemas/girr_ns-1.2.xsd">
    <adminData>
        <creationData creatingUser="duhow" creationDate="2022-04-10_12:47:20" tool="IrScrutinizer" tool2="IrpTransmogrifier" tool2Version="1.2.10" toolVersion="2.3.1"/>
    </adminData>
    <remote comment="Export from IrScrutinizer" displayName="Deco 4K V2" manufacturer="Technicolor" name="remote" remoteName="B526-MMV-AC">
        <commandSet name="commandSet">
            <parameters protocol="NEC1">
                <parameter name="D" value="22"/>
                <parameter name="S" value="32"/>
            </parameters>
            <command F="50" master="parameters" name="EPG">
                <raw frequency="38400">
                    <intro>+9024 -4512 +564 -564 +564 -1692 +564 -1692 +564 -564 +564 -1692 +564 -564 +564 -564 +564 -564 +564 -564 +564 -564 +564 -564 +564 -564 +564 -564 +564 -1692 +564 -564 +564 -564 +564 -564 +564 -1692 +564 -564 +564 -564 +564 -1692 +564 -1692 +564 -564 +564 -564 +564 -1692 +564 -564 +564 -1692 +564 -1692 +564 -564 +564 -564 +564 -1692 +564 -1692 +564 -44268</intro>
                    <repeat>+9024 -2256 +564 -96156</repeat>
                </raw>
                <ccf>0000 006C 0022 0002 015B 00AD 0016 0016 0016 0041 0016 0041 0016 0016 0016 0041 0016 0016 0016 0016 0016 0016 0016 0016 0016 0016 0016 0016 0016 0016 0016 0016 0016 0041 0016 0016 0016 0016 0016 0016 0016 0041 0016 0016 0016 0016 0016 0041 0016 0041 0016 0016 0016 0016 0016 0041 0016 0016 0016 0041 0016 0041 0016 0016 0016 0016 0016 0041 0016 0041 0016 06A4 015B 0057 0016 0E6C</ccf>
            </command>
            <command F="33" master="parameters" name="Power">
                <raw frequency="38400">
                    <intro>+9024 -4512 +564 -564 +564 -1692 +564 -1692 +564 -564 +564 -1692 +564 -564 +564 -564 +564 -564 +564 -564 +564 -564 +564 -564 +564 -564 +564 -564 +564 -1692 +564 -564 +564 -564 +564 -1692 +564 -564 +564 -564 +564 -564 +564 -564 +564 -1692 +564 -564 +564 -564 +564 -564 +564 -1692 +564 -1692 +564 -1692 +564 -1692 +564 -564 +564 -1692 +564 -1692 +564 -44268</intro>
                    <repeat>+9024 -2256 +564 -96156</repeat>
                </raw>
                <ccf>0000 006C 0022 0002 015B 00AD 0016 0016 0016 0041 0016 0041 0016 0016 0016 0041 0016 0016 0016 0016 0016 0016 0016 0016 0016 0016 0016 0016 0016 0016 0016 0016 0016 0041 0016 0016 0016 0016 0016 0041 0016 0016 0016 0016 0016 0016 0016 0016 0016 0041 0016 0016 0016 0016 0016 0016 0016 0041 0016 0041 0016 0041 0016 0041 0016 0016 0016 0041 0016 0041 0016 06A4 015B 0057 0016 0E6C</ccf>
            </command>
            <command F="21" master="parameters" name="Arrow Up">
                <raw frequency="38400">
                    <intro>+9024 -4512 +564 -564 +564 -1692 +564 -1692 +564 -564 +564 -1692 +564 -564 +564 -564 +564 -564 +564 -564 +564 -564 +564 -564 +564 -564 +564 -564 +564 -1692 +564 -564 +564 -564 +564 -1692 +564 -564 +564 -1692 +564 -564 +564 -1692 +564 -564 +564 -564 +564 -564 +564 -564 +564 -1692 +564 -564 +564 -1692 +564 -564 +564 -1692 +564 -1692 +564 -1692 +564 -44268</intro>
                    <repeat>+9024 -2256 +564 -96156</repeat>
                </raw>
                <ccf>0000 006C 0022 0002 015B 00AD 0016 0016 0016 0041 0016 0041 0016 0016 0016 0041 0016 0016 0016 0016 0016 0016 0016 0016 0016 0016 0016 0016 0016 0016 0016 0016 0016 0041 0016 0016 0016 0016 0016 0041 0016 0016 0016 0041 0016 0016 0016 0041 0016 0016 0016 0016 0016 0016 0016 0016 0016 0041 0016 0016 0016 0041 0016 0016 0016 0041 0016 0041 0016 0041 0016 06A4 015B 0057 0016 0E6C</ccf>
            </command>
            <command F="22" master="parameters" name="Arrow Down">
                <raw frequency="38400">
                    <intro>+9024 -4512 +564 -564 +564 -1692 +564 -1692 +564 -564 +564 -1692 +564 -564 +564 -564 +564 -564 +564 -564 +564 -564 +564 -564 +564 -564 +564 -564 +564 -1692 +564 -564 +564 -564 +564 -564 +564 -1692 +564 -1692 +564 -564 +564 -1692 +564 -564 +564 -564 +564 -564 +564 -1692 +564 -564 +564 -564 +564 -1692 +564 -564 +564 -1692 +564 -1692 +564 -1692 +564 -44268</intro>
                    <repeat>+9024 -2256 +564 -96156</repeat>
                </raw>
                <ccf>0000 006C 0022 0002 015B 00AD 0016 0016 0016 0041 0016 0041 0016 0016 0016 0041 0016 0016 0016 0016 0016 0016 0016 0016 0016 0016 0016 0016 0016 0016 0016 0016 0016 0041 0016 0016 0016 0016 0016 0016 0016 0041 0016 0041 0016 0016 0016 0041 0016 0016 0016 0016 0016 0016 0016 0041 0016 0016 0016 0016 0016 0041 0016 0016 0016 0041 0016 0041 0016 0041 0016 06A4 015B 0057 0016 0E6C</ccf>
            </command>
            <command F="23" master="parameters" name="Arrow Left">
                <raw frequency="38400">
                    <intro>+9024 -4512 +564 -564 +564 -1692 +564 -1692 +564 -564 +564 -1692 +564 -564 +564 -564 +564 -564 +564 -564 +564 -564 +564 -564 +564 -564 +564 -564 +564 -1692 +564 -564 +564 -564 +564 -1692 +564 -1692 +564 -1692 +564 -564 +564 -1692 +564 -564 +564 -564 +564 -564 +564 -564 +564 -564 +564 -564 +564 -1692 +564 -564 +564 -1692 +564 -1692 +564 -1692 +564 -44268</intro>
                    <repeat>+9024 -2256 +564 -96156</repeat>
                </raw>
                <ccf>0000 006C 0022 0002 015B 00AD 0016 0016 0016 0041 0016 0041 0016 0016 0016 0041 0016 0016 0016 0016 0016 0016 0016 0016 0016 0016 0016 0016 0016 0016 0016 0016 0016 0041 0016 0016 0016 0016 0016 0041 0016 0041 0016 0041 0016 0016 0016 0041 0016 0016 0016 0016 0016 0016 0016 0016 0016 0016 0016 0016 0016 0041 0016 0016 0016 0041 0016 0041 0016 0041 0016 06A4 015B 0057 0016 0E6C</ccf>
            </command>
            <command F="24" master="parameters" name="Arrow Right">
                <raw frequency="38400">
                    <intro>+9024 -4512 +564 -564 +564 -1692 +564 -1692 +564 -564 +564 -1692 +564 -564 +564 -564 +564 -564 +564 -564 +564 -564 +564 -564 +564 -564 +564 -564 +564 -1692 +564 -564 +564 -564 +564 -564 +564 -564 +564 -564 +564 -1692 +564 -1692 +564 -564 +564 -564 +564 -564 +564 -1692 +564 -1692 +564 -1692 +564 -564 +564 -564 +564 -1692 +564 -1692 +564 -1692 +564 -44268</intro>
                    <repeat>+9024 -2256 +564 -96156</repeat>
                </raw>
                <ccf>0000 006C 0022 0002 015B 00AD 0016 0016 0016 0041 0016 0041 0016 0016 0016 0041 0016 0016 0016 0016 0016 0016 0016 0016 0016 0016 0016 0016 0016 0016 0016 0016 0016 0041 0016 0016 0016 0016 0016 0016 0016 0016 0016 0016 0016 0041 0016 0041 0016 0016 0016 0016 0016 0016 0016 0041 0016 0041 0016 0041 0016 0016 0016 0016 0016 0041 0016 0041 0016 0041 0016 06A4 015B 0057 0016 0E6C</ccf>
            </command>
            <command F="25" master="parameters" name="OK">
                <raw frequency="38400">
                    <intro>+9024 -4512 +564 -564 +564 -1692 +564 -1692 +564 -564 +564 -1692 +564 -564 +564 -564 +564 -564 +564 -564 +564 -564 +564 -564 +564 -564 +564 -564 +564 -1692 +564 -564 +564 -564 +564 -1692 +564 -564 +564 -564 +564 -1692 +564 -1692 +564 -564 +564 -564 +564 -564 +564 -564 +564 -1692 +564 -1692 +564 -564 +564 -564 +564 -1692 +564 -1692 +564 -1692 +564 -44268</intro>
                    <repeat>+9024 -2256 +564 -96156</repeat>
                </raw>
                <ccf>0000 006C 0022 0002 015B 00AD 0016 0016 0016 0041 0016 0041 0016 0016 0016 0041 0016 0016 0016 0016 0016 0016 0016 0016 0016 0016 0016 0016 0016 0016 0016 0016 0016 0041 0016 0016 0016 0016 0016 0041 0016 0016 0016 0016 0016 0041 0016 0041 0016 0016 0016 0016 0016 0016 0016 0016 0016 0041 0016 0041 0016 0016 0016 0016 0016 0041 0016 0041 0016 0041 0016 06A4 015B 0057 0016 0E6C</ccf>
            </command>
            <command F="72" master="parameters" name="Back">
                <raw frequency="38400">
                    <intro>+9024 -4512 +564 -564 +564 -1692 +564 -1692 +564 -564 +564 -1692 +564 -564 +564 -564 +564 -564 +564 -564 +564 -564 +564 -564 +564 -564 +564 -564 +564 -1692 +564 -564 +564 -564 +564 -564 +564 -564 +564 -564 +564 -1692 +564 -564 +564 -564 +564 -1692 +564 -564 +564 -1692 +564 -1692 +564 -1692 +564 -564 +564 -1692 +564 -1692 +564 -564 +564 -1692 +564 -44268</intro>
                    <repeat>+9024 -2256 +564 -96156</repeat>
                </raw>
                <ccf>0000 006C 0022 0002 015B 00AD 0016 0016 0016 0041 0016 0041 0016 0016 0016 0041 0016 0016 0016 0016 0016 0016 0016 0016 0016 0016 0016 0016 0016 0016 0016 0016 0016 0041 0016 0016 0016 0016 0016 0016 0016 0016 0016 0016 0016 0041 0016 0016 0016 0016 0016 0041 0016 0016 0016 0041 0016 0041 0016 0041 0016 0016 0016 0041 0016 0041 0016 0016 0016 0041 0016 06A4 015B 0057 0016 0E6C</ccf>
            </command>
            <command F="71" master="parameters" name="Home">
                <raw frequency="38400">
                    <intro>+9024 -4512 +564 -564 +564 -1692 +564 -1692 +564 -564 +564 -1692 +564 -564 +564 -564 +564 -564 +564 -564 +564 -564 +564 -564 +564 -564 +564 -564 +564 -1692 +564 -564 +564 -564 +564 -1692 +564 -1692 +564 -1692 +564 -564 +564 -564 +564 -564 +564 -1692 +564 -564 +564 -564 +564 -564 +564 -564 +564 -1692 +564 -1692 +564 -1692 +564 -564 +564 -1692 +564 -44268</intro>
                    <repeat>+9024 -2256 +564 -96156</repeat>
                </raw>
                <ccf>0000 006C 0022 0002 015B 00AD 0016 0016 0016 0041 0016 0041 0016 0016 0016 0041 0016 0016 0016 0016 0016 0016 0016 0016 0016 0016 0016 0016 0016 0016 0016 0016 0016 0041 0016 0016 0016 0016 0016 0041 0016 0041 0016 0041 0016 0016 0016 0016 0016 0016 0016 0041 0016 0016 0016 0016 0016 0016 0016 0016 0016 0041 0016 0041 0016 0041 0016 0016 0016 0041 0016 06A4 015B 0057 0016 0E6C</ccf>
            </command>
            <command F="97" master="parameters" name="Green Play">
                <raw frequency="38400">
                    <intro>+9024 -4512 +564 -564 +564 -1692 +564 -1692 +564 -564 +564 -1692 +564 -564 +564 -564 +564 -564 +564 -564 +564 -564 +564 -564 +564 -564 +564 -564 +564 -1692 +564 -564 +564 -564 +564 -1692 +564 -564 +564 -564 +564 -564 +564 -564 +564 -1692 +564 -1692 +564 -564 +564 -564 +564 -1692 +564 -1692 +564 -1692 +564 -1692 +564 -564 +564 -564 +564 -1692 +564 -44268</intro>
                    <repeat>+9024 -2256 +564 -96156</repeat>
                </raw>
                <ccf>0000 006C 0022 0002 015B 00AD 0016 0016 0016 0041 0016 0041 0016 0016 0016 0041 0016 0016 0016 0016 0016 0016 0016 0016 0016 0016 0016 0016 0016 0016 0016 0016 0016 0041 0016 0016 0016 0016 0016 0041 0016 0016 0016 0016 0016 0016 0016 0016 0016 0041 0016 0041 0016 0016 0016 0016 0016 0041 0016 0041 0016 0041 0016 0041 0016 0016 0016 0016 0016 0041 0016 06A4 015B 0057 0016 0E6C</ccf>
            </command>
            <command F="70" master="parameters" name="Google Assistant">
                <raw frequency="38400">
                    <intro>+9024 -4512 +564 -564 +564 -1692 +564 -1692 +564 -564 +564 -1692 +564 -564 +564 -564 +564 -564 +564 -564 +564 -564 +564 -564 +564 -564 +564 -564 +564 -1692 +564 -564 +564 -564 +564 -564 +564 -1692 +564 -1692 +564 -564 +564 -564 +564 -564 +564 -1692 +564 -564 +564 -1692 +564 -564 +564 -564 +564 -1692 +564 -1692 +564 -1692 +564 -564 +564 -1692 +564 -44268</intro>
                    <repeat>+9024 -2256 +564 -96156</repeat>
                </raw>
                <ccf>0000 006C 0022 0002 015B 00AD 0016 0016 0016 0041 0016 0041 0016 0016 0016 0041 0016 0016 0016 0016 0016 0016 0016 0016 0016 0016 0016 0016 0016 0016 0016 0016 0016 0041 0016 0016 0016 0016 0016 0016 0016 0041 0016 0041 0016 0016 0016 0016 0016 0016 0016 0041 0016 0016 0016 0041 0016 0016 0016 0016 0016 0041 0016 0041 0016 0041 0016 0016 0016 0041 0016 06A4 015B 0057 0016 0E6C</ccf>
            </command>
            <command F="35" master="parameters" name="Volume Up">
                <raw frequency="38400">
                    <intro>+9024 -4512 +564 -564 +564 -1692 +564 -1692 +564 -564 +564 -1692 +564 -564 +564 -564 +564 -564 +564 -564 +564 -564 +564 -564 +564 -564 +564 -564 +564 -1692 +564 -564 +564 -564 +564 -1692 +564 -1692 +564 -564 +564 -564 +564 -564 +564 -1692 +564 -564 +564 -564 +564 -564 +564 -564 +564 -1692 +564 -1692 +564 -1692 +564 -564 +564 -1692 +564 -1692 +564 -44268</intro>
                    <repeat>+9024 -2256 +564 -96156</repeat>
                </raw>
                <ccf>0000 006C 0022 0002 015B 00AD 0016 0016 0016 0041 0016 0041 0016 0016 0016 0041 0016 0016 0016 0016 0016 0016 0016 0016 0016 0016 0016 0016 0016 0016 0016 0016 0016 0041 0016 0016 0016 0016 0016 0041 0016 0041 0016 0016 0016 0016 0016 0016 0016 0041 0016 0016 0016 0016 0016 0016 0016 0016 0016 0041 0016 0041 0016 0041 0016 0016 0016 0041 0016 0041 0016 06A4 015B 0057 0016 0E6C</ccf>
            </command>
            <command F="36" master="parameters" name="Volume Down">
                <raw frequency="38400">
                    <intro>+9024 -4512 +564 -564 +564 -1692 +564 -1692 +564 -564 +564 -1692 +564 -564 +564 -564 +564 -564 +564 -564 +564 -564 +564 -564 +564 -564 +564 -564 +564 -1692 +564 -564 +564 -564 +564 -564 +564 -564 +564 -1692 +564 -564 +564 -564 +564 -1692 +564 -564 +564 -564 +564 -1692 +564 -1692 +564 -564 +564 -1692 +564 -1692 +564 -564 +564 -1692 +564 -1692 +564 -44268</intro>
                    <repeat>+9024 -2256 +564 -96156</repeat>
                </raw>
                <ccf>0000 006C 0022 0002 015B 00AD 0016 0016 0016 0041 0016 0041 0016 0016 0016 0041 0016 0016 0016 0016 0016 0016 0016 0016 0016 0016 0016 0016 0016 0016 0016 0016 0016 0041 0016 0016 0016 0016 0016 0016 0016 0016 0016 0041 0016 0016 0016 0016 0016 0041 0016 0016 0016 0016 0016 0041 0016 0041 0016 0016 0016 0041 0016 0041 0016 0016 0016 0041 0016 0041 0016 06A4 015B 0057 0016 0E6C</ccf>
            </command>
            <command F="51" master="parameters" name="Channel Up">
                <raw frequency="38400">
                    <intro>+9024 -4512 +564 -564 +564 -1692 +564 -1692 +564 -564 +564 -1692 +564 -564 +564 -564 +564 -564 +564 -564 +564 -564 +564 -564 +564 -564 +564 -564 +564 -1692 +564 -564 +564 -564 +564 -1692 +564 -1692 +564 -564 +564 -564 +564 -1692 +564 -1692 +564 -564 +564 -564 +564 -564 +564 -564 +564 -1692 +564 -1692 +564 -564 +564 -564 +564 -1692 +564 -1692 +564 -44268</intro>
                    <repeat>+9024 -2256 +564 -96156</repeat>
                </raw>
                <ccf>0000 006C 0022 0002 015B 00AD 0016 0016 0016 0041 0016 0041 0016 0016 0016 0041 0016 0016 0016 0016 0016 0016 0016 0016 0016 0016 0016 0016 0016 0016 0016 0016 0016 0041 0016 0016 0016 0016 0016 0041 0016 0041 0016 0016 0016 0016 0016 0041 0016 0041 0016 0016 0016 0016 0016 0016 0016 0016 0016 0041 0016 0041 0016 0016 0016 0016 0016 0041 0016 0041 0016 06A4 015B 0057 0016 0E6C</ccf>
            </command>
            <command F="52" master="parameters" name="Channel Down">
                <raw frequency="38400">
                    <intro>+9024 -4512 +564 -564 +564 -1692 +564 -1692 +564 -564 +564 -1692 +564 -564 +564 -564 +564 -564 +564 -564 +564 -564 +564 -564 +564 -564 +564 -564 +564 -1692 +564 -564 +564 -564 +564 -564 +564 -564 +564 -1692 +564 -564 +564 -1692 +564 -1692 +564 -564 +564 -564 +564 -1692 +564 -1692 +564 -564 +564 -1692 +564 -564 +564 -564 +564 -1692 +564 -1692 +564 -44268</intro>
                    <repeat>+9024 -2256 +564 -96156</repeat>
                </raw>
                <ccf>0000 006C 0022 0002 015B 00AD 0016 0016 0016 0041 0016 0041 0016 0016 0016 0041 0016 0016 0016 0016 0016 0016 0016 0016 0016 0016 0016 0016 0016 0016 0016 0016 0016 0041 0016 0016 0016 0016 0016 0016 0016 0016 0016 0041 0016 0016 0016 0041 0016 0041 0016 0016 0016 0016 0016 0041 0016 0041 0016 0016 0016 0041 0016 0016 0016 0016 0016 0041 0016 0041 0016 06A4 015B 0057 0016 0E6C</ccf>
            </command>
            <command F="75" master="parameters" name="Netflix">
                <raw frequency="38400">
                    <intro>+9024 -4512 +564 -564 +564 -1692 +564 -1692 +564 -564 +564 -1692 +564 -564 +564 -564 +564 -564 +564 -564 +564 -564 +564 -564 +564 -564 +564 -564 +564 -1692 +564 -564 +564 -564 +564 -1692 +564 -1692 +564 -564 +564 -1692 +564 -564 +564 -564 +564 -1692 +564 -564 +564 -564 +564 -564 +564 -1692 +564 -564 +564 -1692 +564 -1692 +564 -564 +564 -1692 +564 -44268</intro>
                    <repeat>+9024 -2256 +564 -96156</repeat>
                </raw>
                <ccf>0000 006C 0022 0002 015B 00AD 0016 0016 0016 0041 0016 0041 0016 0016 0016 0041 0016 0016 0016 0016 0016 0016 0016 0016 0016 0016 0016 0016 0016 0016 0016 0016 0016 0041 0016 0016 0016 0016 0016 0041 0016 0041 0016 0016 0016 0041 0016 0016 0016 0016 0016 0041 0016 0016 0016 0016 0016 0016 0016 0041 0016 0016 0016 0041 0016 0041 0016 0016 0016 0041 0016 06A4 015B 0057 0016 0E6C</ccf>
            </command>
            <command F="74" master="parameters" name="Amazon Prime Video">
                <raw frequency="38400">
                    <intro>+9024 -4512 +564 -564 +564 -1692 +564 -1692 +564 -564 +564 -1692 +564 -564 +564 -564 +564 -564 +564 -564 +564 -564 +564 -564 +564 -564 +564 -564 +564 -1692 +564 -564 +564 -564 +564 -564 +564 -1692 +564 -564 +564 -1692 +564 -564 +564 -564 +564 -1692 +564 -564 +564 -1692 +564 -564 +564 -1692 +564 -564 +564 -1692 +564 -1692 +564 -564 +564 -1692 +564 -44268</intro>
                    <repeat>+9024 -2256 +564 -96156</repeat>
                </raw>
                <ccf>0000 006C 0022 0002 015B 00AD 0016 0016 0016 0041 0016 0041 0016 0016 0016 0041 0016 0016 0016 0016 0016 0016 0016 0016 0016 0016 0016 0016 0016 0016 0016 0016 0016 0041 0016 0016 0016 0016 0016 0016 0016 0041 0016 0016 0016 0041 0016 0016 0016 0016 0016 0041 0016 0016 0016 0041 0016 0016 0016 0041 0016 0016 0016 0041 0016 0041 0016 0016 0016 0041 0016 06A4 015B 0057 0016 0E6C</ccf>
            </command>
            <command F="187" master="parameters" name="Applications">
                <raw frequency="38400">
                    <intro>+9024 -4512 +564 -564 +564 -1692 +564 -1692 +564 -564 +564 -1692 +564 -564 +564 -564 +564 -564 +564 -564 +564 -564 +564 -564 +564 -564 +564 -564 +564 -1692 +564 -564 +564 -564 +564 -1692 +564 -1692 +564 -564 +564 -1692 +564 -1692 +564 -1692 +564 -564 +564 -1692 +564 -564 +564 -564 +564 -1692 +564 -564 +564 -564 +564 -564 +564 -1692 +564 -564 +564 -44268</intro>
                    <repeat>+9024 -2256 +564 -96156</repeat>
                </raw>
                <ccf>0000 006C 0022 0002 015B 00AD 0016 0016 0016 0041 0016 0041 0016 0016 0016 0041 0016 0016 0016 0016 0016 0016 0016 0016 0016 0016 0016 0016 0016 0016 0016 0016 0016 0041 0016 0016 0016 0016 0016 0041 0016 0041 0016 0016 0016 0041 0016 0041 0016 0041 0016 0016 0016 0041 0016 0016 0016 0016 0016 0041 0016 0016 0016 0016 0016 0016 0016 0041 0016 0016 0016 06A4 015B 0057 0016 0E6C</ccf>
            </command>
            <command F="1" master="parameters" name="Input 1">
                <raw frequency="38400">
                    <intro>+9024 -4512 +564 -564 +564 -1692 +564 -1692 +564 -564 +564 -1692 +564 -564 +564 -564 +564 -564 +564 -564 +564 -564 +564 -564 +564 -564 +564 -564 +564 -1692 +564 -564 +564 -564 +564 -1692 +564 -564 +564 -564 +564 -564 +564 -564 +564 -564 +564 -564 +564 -564 +564 -564 +564 -1692 +564 -1692 +564 -1692 +564 -1692 +564 -1692 +564 -1692 +564 -1692 +564 -44268</intro>
                    <repeat>+9024 -2256 +564 -96156</repeat>
                </raw>
                <ccf>0000 006C 0022 0002 015B 00AD 0016 0016 0016 0041 0016 0041 0016 0016 0016 0041 0016 0016 0016 0016 0016 0016 0016 0016 0016 0016 0016 0016 0016 0016 0016 0016 0016 0041 0016 0016 0016 0016 0016 0041 0016 0016 0016 0016 0016 0016 0016 0016 0016 0016 0016 0016 0016 0016 0016 0016 0016 0041 0016 0041 0016 0041 0016 0041 0016 0041 0016 0041 0016 0041 0016 06A4 015B 0057 0016 0E6C</ccf>
            </command>
            <command F="2" master="parameters" name="Input 2">
                <raw frequency="38400">
                    <intro>+9024 -4512 +564 -564 +564 -1692 +564 -1692 +564 -564 +564 -1692 +564 -564 +564 -564 +564 -564 +564 -564 +564 -564 +564 -564 +564 -564 +564 -564 +564 -1692 +564 -564 +564 -564 +564 -564 +564 -1692 +564 -564 +564 -564 +564 -564 +564 -564 +564 -564 +564 -564 +564 -1692 +564 -564 +564 -1692 +564 -1692 +564 -1692 +564 -1692 +564 -1692 +564 -1692 +564 -44268</intro>
                    <repeat>+9024 -2256 +564 -96156</repeat>
                </raw>
                <ccf>0000 006C 0022 0002 015B 00AD 0016 0016 0016 0041 0016 0041 0016 0016 0016 0041 0016 0016 0016 0016 0016 0016 0016 0016 0016 0016 0016 0016 0016 0016 0016 0016 0016 0041 0016 0016 0016 0016 0016 0016 0016 0041 0016 0016 0016 0016 0016 0016 0016 0016 0016 0016 0016 0016 0016 0041 0016 0016 0016 0041 0016 0041 0016 0041 0016 0041 0016 0041 0016 0041 0016 06A4 015B 0057 0016 0E6C</ccf>
            </command>
            <command F="3" master="parameters" name="Input 3">
                <raw frequency="38400">
                    <intro>+9024 -4512 +564 -564 +564 -1692 +564 -1692 +564 -564 +564 -1692 +564 -564 +564 -564 +564 -564 +564 -564 +564 -564 +564 -564 +564 -564 +564 -564 +564 -1692 +564 -564 +564 -564 +564 -1692 +564 -1692 +564 -564 +564 -564 +564 -564 +564 -564 +564 -564 +564 -564 +564 -564 +564 -564 +564 -1692 +564 -1692 +564 -1692 +564 -1692 +564 -1692 +564 -1692 +564 -44268</intro>
                    <repeat>+9024 -2256 +564 -96156</repeat>
                </raw>
                <ccf>0000 006C 0022 0002 015B 00AD 0016 0016 0016 0041 0016 0041 0016 0016 0016 0041 0016 0016 0016 0016 0016 0016 0016 0016 0016 0016 0016 0016 0016 0016 0016 0016 0016 0041 0016 0016 0016 0016 0016 0041 0016 0041 0016 0016 0016 0016 0016 0016 0016 0016 0016 0016 0016 0016 0016 0016 0016 0016 0016 0041 0016 0041 0016 0041 0016 0041 0016 0041 0016 0041 0016 06A4 015B 0057 0016 0E6C</ccf>
            </command>
            <command F="4" master="parameters" name="Input 4">
                <raw frequency="38400">
                    <intro>+9024 -4512 +564 -564 +564 -1692 +564 -1692 +564 -564 +564 -1692 +564 -564 +564 -564 +564 -564 +564 -564 +564 -564 +564 -564 +564 -564 +564 -564 +564 -1692 +564 -564 +564 -564 +564 -564 +564 -564 +564 -1692 +564 -564 +564 -564 +564 -564 +564 -564 +564 -564 +564 -1692 +564 -1692 +564 -564 +564 -1692 +564 -1692 +564 -1692 +564 -1692 +564 -1692 +564 -44268</intro>
                    <repeat>+9024 -2256 +564 -96156</repeat>
                </raw>
                <ccf>0000 006C 0022 0002 015B 00AD 0016 0016 0016 0041 0016 0041 0016 0016 0016 0041 0016 0016 0016 0016 0016 0016 0016 0016 0016 0016 0016 0016 0016 0016 0016 0016 0016 0041 0016 0016 0016 0016 0016 0016 0016 0016 0016 0041 0016 0016 0016 0016 0016 0016 0016 0016 0016 0016 0016 0041 0016 0041 0016 0016 0016 0041 0016 0041 0016 0041 0016 0041 0016 0041 0016 06A4 015B 0057 0016 0E6C</ccf>
            </command>
            <command F="5" master="parameters" name="Input 5">
                <raw frequency="38400">
                    <intro>+9024 -4512 +564 -564 +564 -1692 +564 -1692 +564 -564 +564 -1692 +564 -564 +564 -564 +564 -564 +564 -564 +564 -564 +564 -564 +564 -564 +564 -564 +564 -1692 +564 -564 +564 -564 +564 -1692 +564 -564 +564 -1692 +564 -564 +564 -564 +564 -564 +564 -564 +564 -564 +564 -564 +564 -1692 +564 -564 +564 -1692 +564 -1692 +564 -1692 +564 -1692 +564 -1692 +564 -44268</intro>
                    <repeat>+9024 -2256 +564 -96156</repeat>
                </raw>
                <ccf>0000 006C 0022 0002 015B 00AD 0016 0016 0016 0041 0016 0041 0016 0016 0016 0041 0016 0016 0016 0016 0016 0016 0016 0016 0016 0016 0016 0016 0016 0016 0016 0016 0016 0041 0016 0016 0016 0016 0016 0041 0016 0016 0016 0041 0016 0016 0016 0016 0016 0016 0016 0016 0016 0016 0016 0016 0016 0041 0016 0016 0016 0041 0016 0041 0016 0041 0016 0041 0016 0041 0016 06A4 015B 0057 0016 0E6C</ccf>
            </command>
            <command F="6" master="parameters" name="Input 6">
                <raw frequency="38400">
                    <intro>+9024 -4512 +564 -564 +564 -1692 +564 -1692 +564 -564 +564 -1692 +564 -564 +564 -564 +564 -564 +564 -564 +564 -564 +564 -564 +564 -564 +564 -564 +564 -1692 +564 -564 +564 -564 +564 -564 +564 -1692 +564 -1692 +564 -564 +564 -564 +564 -564 +564 -564 +564 -564 +564 -1692 +564 -564 +564 -564 +564 -1692 +564 -1692 +564 -1692 +564 -1692 +564 -1692 +564 -44268</intro>
                    <repeat>+9024 -2256 +564 -96156</repeat>
                </raw>
                <ccf>0000 006C 0022 0002 015B 00AD 0016 0016 0016 0041 0016 0041 0016 0016 0016 0041 0016 0016 0016 0016 0016 0016 0016 0016 0016 0016 0016 0016 0016 0016 0016 0016 0016 0041 0016 0016 0016 0016 0016 0016 0016 0041 0016 0041 0016 0016 0016 0016 0016 0016 0016 0016 0016 0016 0016 0041 0016 0016 0016 0016 0016 0041 0016 0041 0016 0041 0016 0041 0016 0041 0016 06A4 015B 0057 0016 0E6C</ccf>
            </command>
            <command F="7" master="parameters" name="Input 7">
                <raw frequency="38400">
                    <intro>+9024 -4512 +564 -564 +564 -1692 +564 -1692 +564 -564 +564 -1692 +564 -564 +564 -564 +564 -564 +564 -564 +564 -564 +564 -564 +564 -564 +564 -564 +564 -1692 +564 -564 +564 -564 +564 -1692 +564 -1692 +564 -1692 +564 -564 +564 -564 +564 -564 +564 -564 +564 -564 +564 -564 +564 -564 +564 -564 +564 -1692 +564 -1692 +564 -1692 +564 -1692 +564 -1692 +564 -44268</intro>
                    <repeat>+9024 -2256 +564 -96156</repeat>
                </raw>
                <ccf>0000 006C 0022 0002 015B 00AD 0016 0016 0016 0041 0016 0041 0016 0016 0016 0041 0016 0016 0016 0016 0016 0016 0016 0016 0016 0016 0016 0016 0016 0016 0016 0016 0016 0041 0016 0016 0016 0016 0016 0041 0016 0041 0016 0041 0016 0016 0016 0016 0016 0016 0016 0016 0016 0016 0016 0016 0016 0016 0016 0016 0016 0041 0016 0041 0016 0041 0016 0041 0016 0041 0016 06A4 015B 0057 0016 0E6C</ccf>
            </command>
            <command F="8" master="parameters" name="Input 8">
                <raw frequency="38400">
                    <intro>+9024 -4512 +564 -564 +564 -1692 +564 -1692 +564 -564 +564 -1692 +564 -564 +564 -564 +564 -564 +564 -564 +564 -564 +564 -564 +564 -564 +564 -564 +564 -1692 +564 -564 +564 -564 +564 -564 +564 -564 +564 -564 +564 -1692 +564 -564 +564 -564 +564 -564 +564 -564 +564 -1692 +564 -1692 +564 -1692 +564 -564 +564 -1692 +564 -1692 +564 -1692 +564 -1692 +564 -44268</intro>
                    <repeat>+9024 -2256 +564 -96156</repeat>
                </raw>
                <ccf>0000 006C 0022 0002 015B 00AD 0016 0016 0016 0041 0016 0041 0016 0016 0016 0041 0016 0016 0016 0016 0016 0016 0016 0016 0016 0016 0016 0016 0016 0016 0016 0016 0016 0041 0016 0016 0016 0016 0016 0016 0016 0016 0016 0016 0016 0041 0016 0016 0016 0016 0016 0016 0016 0016 0016 0041 0016 0041 0016 0041 0016 0016 0016 0041 0016 0041 0016 0041 0016 0041 0016 06A4 015B 0057 0016 0E6C</ccf>
            </command>
            <command F="9" master="parameters" name="Input 9">
                <raw frequency="38400">
                    <intro>+9024 -4512 +564 -564 +564 -1692 +564 -1692 +564 -564 +564 -1692 +564 -564 +564 -564 +564 -564 +564 -564 +564 -564 +564 -564 +564 -564 +564 -564 +564 -1692 +564 -564 +564 -564 +564 -1692 +564 -564 +564 -564 +564 -1692 +564 -564 +564 -564 +564 -564 +564 -564 +564 -564 +564 -1692 +564 -1692 +564 -564 +564 -1692 +564 -1692 +564 -1692 +564 -1692 +564 -44268</intro>
                    <repeat>+9024 -2256 +564 -96156</repeat>
                </raw>
                <ccf>0000 006C 0022 0002 015B 00AD 0016 0016 0016 0041 0016 0041 0016 0016 0016 0041 0016 0016 0016 0016 0016 0016 0016 0016 0016 0016 0016 0016 0016 0016 0016 0016 0016 0041 0016 0016 0016 0016 0016 0041 0016 0016 0016 0016 0016 0041 0016 0016 0016 0016 0016 0016 0016 0016 0016 0016 0016 0041 0016 0041 0016 0016 0016 0041 0016 0041 0016 0041 0016 0041 0016 06A4 015B 0057 0016 0E6C</ccf>
            </command>
            <command F="10" master="parameters" name="Input 0">
                <raw frequency="38400">
                    <intro>+9024 -4512 +564 -564 +564 -1692 +564 -1692 +564 -564 +564 -1692 +564 -564 +564 -564 +564 -564 +564 -564 +564 -564 +564 -564 +564 -564 +564 -564 +564 -1692 +564 -564 +564 -564 +564 -564 +564 -1692 +564 -564 +564 -1692 +564 -564 +564 -564 +564 -564 +564 -564 +564 -1692 +564 -564 +564 -1692 +564 -564 +564 -1692 +564 -1692 +564 -1692 +564 -1692 +564 -44268</intro>
                    <repeat>+9024 -2256 +564 -96156</repeat>
                </raw>
                <ccf>0000 006C 0022 0002 015B 00AD 0016 0016 0016 0041 0016 0041 0016 0016 0016 0041 0016 0016 0016 0016 0016 0016 0016 0016 0016 0016 0016 0016 0016 0016 0016 0016 0016 0041 0016 0016 0016 0016 0016 0016 0016 0041 0016 0016 0016 0041 0016 0016 0016 0016 0016 0016 0016 0016 0016 0041 0016 0016 0016 0041 0016 0016 0016 0041 0016 0041 0016 0041 0016 0041 0016 06A4 015B 0057 0016 0E6C</ccf>
            </command>
            <command F="37" master="parameters" name="Mute">
                <raw frequency="38400">
                    <intro>+9024 -4512 +564 -564 +564 -1692 +564 -1692 +564 -564 +564 -1692 +564 -564 +564 -564 +564 -564 +564 -564 +564 -564 +564 -564 +564 -564 +564 -564 +564 -1692 +564 -564 +564 -564 +564 -1692 +564 -564 +564 -1692 +564 -564 +564 -564 +564 -1692 +564 -564 +564 -564 +564 -564 +564 -1692 +564 -564 +564 -1692 +564 -1692 +564 -564 +564 -1692 +564 -1692 +564 -44268</intro>
                    <repeat>+9024 -2256 +564 -96156</repeat>
                </raw>
                <ccf>0000 006C 0022 0002 015B 00AD 0016 0016 0016 0041 0016 0041 0016 0016 0016 0041 0016 0016 0016 0016 0016 0016 0016 0016 0016 0016 0016 0016 0016 0016 0016 0016 0016 0041 0016 0016 0016 0016 0016 0041 0016 0016 0016 0041 0016 0016 0016 0016 0016 0041 0016 0016 0016 0016 0016 0016 0016 0041 0016 0016 0016 0041 0016 0041 0016 0016 0016 0041 0016 0041 0016 06A4 015B 0057 0016 0E6C</ccf>
            </command>
            <command F="73" master="parameters" name="Record">
                <raw frequency="38400">
                    <intro>+9024 -4512 +564 -564 +564 -1692 +564 -1692 +564 -564 +564 -1692 +564 -564 +564 -564 +564 -564 +564 -564 +564 -564 +564 -564 +564 -564 +564 -564 +564 -1692 +564 -564 +564 -564 +564 -1692 +564 -564 +564 -564 +564 -1692 +564 -564 +564 -564 +564 -1692 +564 -564 +564 -564 +564 -1692 +564 -1692 +564 -564 +564 -1692 +564 -1692 +564 -564 +564 -1692 +564 -44268</intro>
                    <repeat>+9024 -2256 +564 -96156</repeat>
                </raw>
                <ccf>0000 006C 0022 0002 015B 00AD 0016 0016 0016 0041 0016 0041 0016 0016 0016 0041 0016 0016 0016 0016 0016 0016 0016 0016 0016 0016 0016 0016 0016 0016 0016 0016 0016 0041 0016 0016 0016 0016 0016 0041 0016 0016 0016 0016 0016 0041 0016 0016 0016 0016 0016 0041 0016 0016 0016 0016 0016 0041 0016 0041 0016 0016 0016 0041 0016 0041 0016 0016 0016 0041 0016 06A4 015B 0057 0016 0E6C</ccf>
            </command>
        </commandSet>
    </remote>
</remotes>
